README.rst
setup.py
semawal/__init__.py
semawal/json_parser.py
semawal/net.py
semawal/node.py
semawal/semaweb.py
semawal.egg-info/PKG-INFO
semawal.egg-info/SOURCES.txt
semawal.egg-info/dependency_links.txt
semawal.egg-info/top_level.txt