Metadata-Version: 1.1
Name: semawal
Version: 0.2.2
Summary: SemaWal: Semantic Network Resolver
Home-page: https://40uf411.github.io/SemaWal/
Author: Ali Aouf
Author-email: 40uf4l1@gmail.com
License: GPL
Platform: UNKNOWN
Classifier: Development Status :: 5 - Production/Stable
Classifier: Intended Audience :: End Users/Desktop
Classifier: Operating System :: OS Independent
Classifier: Programming Language :: Python
